{
  "todoList": [
    {
      "category": "Personal",
      "task": "Water plants",
      "date": "2022-12-25T22:00:00.000Z",
      "tags": [
        "plants",
        "water"
      ],
      "authorId": 1,
      "checked": false,
      "id": 1
    },
    {
      "category": "Work",
      "task": "Create new task for my to-do list",
      "date": "2022-12-28T22:00:00.000Z",
      "tags": [
        "new task"
      ],
      "authorId": 1,
      "checked": false,
      "id": 2
    },
    {
      "category": "Personal",
      "task": "Create music list",
      "date": "2022-12-29T22:00:00.000Z",
      "tags": [
        "music"
      ],
      "authorId": 1,
      "checked": false,
      "id": 3
    }
  ],
  "users": [
    {
      "name": "Anna",
      "email": "anna@gmail.com",
      "userId": 1,
      "id": 1
    }
  ]
}